LICENSE
MANIFEST.in
README.rst
setup.py
jinja2schema/__init__.py
jinja2schema/_compat.py
jinja2schema/config.py
jinja2schema/core.py
jinja2schema/exceptions.py
jinja2schema/macro.py
jinja2schema/mergers.py
jinja2schema/model.py
jinja2schema/order_number.py
jinja2schema/util.py
jinja2schema.egg-info/PKG-INFO
jinja2schema.egg-info/SOURCES.txt
jinja2schema.egg-info/dependency_links.txt
jinja2schema.egg-info/requires.txt
jinja2schema.egg-info/top_level.txt
jinja2schema/visitors/__init__.py
jinja2schema/visitors/expr.py
jinja2schema/visitors/stmt.py
jinja2schema/visitors/util.py