Metadata-Version: 1.1
Name: jinja2schema
Version: 0.1.4
Summary: Type inference for Jinja2 templates.
Home-page: https://jinja2schema.readthedocs.io
Author: Anton Romanovich
Author-email: anthony.romanovich@gmail.com
License: Copyright (c) 2014 by Anton Romanovich.
